volosti/__init__.py
volosti-0.1.dev2.dist-info/LICENSE
volosti-0.1.dev2.dist-info/WHEEL
volosti-0.1.dev2.dist-info/METADATA
volosti-0.1.dev2.dist-info/RECORD
